find_couplings/__init__.py
find_couplings/find_couplings.py
find_couplings-0.1.dist-info/METADATA
find_couplings-0.1.dist-info/WHEEL
find_couplings-0.1.dist-info/top_level.txt
find_couplings-0.1.dist-info/RECORD
